bibliograph/ParsedShorthand.py
bibliograph/Shorthand.py
bibliograph/TextNet.py
bibliograph/__init__.py
bibliograph/alias_generators.py
bibliograph/core.py
bibliograph/entry_parsing.py
bibliograph/syntax_parsing.py
bibliograph/tests.py
bibliograph/util.py
bibliograph-0.1.0.dist-info/LICENSE
bibliograph-0.1.0.dist-info/METADATA
bibliograph-0.1.0.dist-info/WHEEL
bibliograph-0.1.0.dist-info/top_level.txt
bibliograph-0.1.0.dist-info/RECORD
