Metadata-Version: 2.1
Name: bibliograph
Version: 0.1.0
Summary: A database system for research in the humanities
Home-page: https://github.com/shortorian/bibliograph
Author: Devin Short
Author-email: short.devin@gmail.com
License: MIT
Classifier: Development Status :: 4 - Beta
Classifier: License :: OSI Approved :: MIT License
Classifier: Natural Language :: English
Requires-Python: >=3
License-File: LICENSE
Requires-Dist: attrs (>=22.1.0)
Requires-Dist: bibtexparser (>=1.4.0)
Requires-Dist: colorama (>=0.4.6)
Requires-Dist: exceptiongroup (>=1.0.0rc9)
Requires-Dist: iniconfig (>=1.1.1)
Requires-Dist: numpy (>=1.23.4)
Requires-Dist: packaging (>=21.3)
Requires-Dist: pandas (>=1.5.1)
Requires-Dist: pluggy (>=1.0.0)
Requires-Dist: pyparsing (>=3.0.9)
Requires-Dist: pytest (>=7.2.0)
Requires-Dist: python-dateutil (>=2.8.2)
Requires-Dist: pytz (>=2022.5)
Requires-Dist: six (>=1.16.0)
Requires-Dist: tomli (>=2.0.1)
